pystarling-0.0.5.dist-info/METADATA
pystarling-0.0.5.dist-info/RECORD
pystarling-0.0.5.dist-info/WHEEL
pystarling-0.0.5.dist-info/top_level.txt
starling/__init__.py
starling/errors.py
starling/starling.py
starling/entities/__init__.py
starling/entities/account.py
starling/entities/address.py
starling/entities/card.py
starling/entities/contact.py
starling/entities/customer.py
starling/entities/mandate.py
starling/entities/oauth.py
starling/entities/payment.py
starling/entities/savingsgoals.py
starling/entities/transaction.py
starling/entities/whoami.py
starling/utils/__init__.py
starling/utils/http.py
starling/utils/request.py
starling/utils/validator.py
test/__init__.py
test/test_oauth_spec.py
test/test_starling_spec.py
test/testsupport.py
